keyboardstream2py/__init__.py
keyboardstream2py/getch.py
keyboardstream2py/keyboard_input.py
keyboardstream2py-0.0.2.dist-info/LICENSE
keyboardstream2py-0.0.2.dist-info/METADATA
keyboardstream2py-0.0.2.dist-info/WHEEL
keyboardstream2py-0.0.2.dist-info/top_level.txt
keyboardstream2py-0.0.2.dist-info/RECORD
