Metadata-Version: 2.1
Name: keyboardstream2py
Version: 0.0.2
Summary: stream2py interface for keyboard inputs
Home-page: https://github.com/i2mint/keyboardstream2py
Author: OtoSense
License: apache-2.0
Platform: any
